pytorch_fid_wrapper/__init__.py
pytorch_fid_wrapper/fid_score.py
pytorch_fid_wrapper/inception.py
pytorch_fid_wrapper/params.py
pytorch_fid_wrapper-0.0.4.dist-info/LICENSE
pytorch_fid_wrapper-0.0.4.dist-info/METADATA
pytorch_fid_wrapper-0.0.4.dist-info/WHEEL
pytorch_fid_wrapper-0.0.4.dist-info/top_level.txt
pytorch_fid_wrapper-0.0.4.dist-info/RECORD
