Metadata-Version: 2.1
Name: pytorch-fid-wrapper
Version: 0.0.4
Summary: Wrapper around the pytorch-fid package to compute Frechet InceptionDistance (FID) using PyTorch in-memory given tensors of images.
Home-page: https://github.com/vict0rsch/pytorch-fid-wrapper
Author: Victor Schmidt
Author-email: not.an.address@yes.com
License: UNKNOWN
Platform: UNKNOWN
Classifier: Programming Language :: Python :: 3
Classifier: License :: OSI Approved :: Apache Software License
Requires-Python: >=3.5
Requires-Dist: numpy
Requires-Dist: pillow
Requires-Dist: scipy
Requires-Dist: torch
Requires-Dist: torchvision
